flask_trace/__init__.py
flask_trace-0.0.3.dist-info/WHEEL
flask_trace-0.0.3.dist-info/DESCRIPTION.rst
flask_trace-0.0.3.dist-info/RECORD
flask_trace-0.0.3.dist-info/metadata.json
flask_trace-0.0.3.dist-info/top_level.txt
flask_trace-0.0.3.dist-info/METADATA
