Metadata-Version: 2.0
Name: flask-trace
Version: 0.0.3
Summary: Log trace decorator function for Flask
Home-page: https://github.com/canassa/flask-trace
Author: Cesar Canassa
Author-email: cesar@canassa.com
License: MIT
Keywords: flask log trace logging
Platform: UNKNOWN
Classifier: Development Status :: 3 - Alpha
Classifier: Intended Audience :: Developers
Classifier: Intended Audience :: System Administrators
Classifier: Topic :: Software Development :: Libraries
Classifier: Topic :: Software Development :: User Interfaces
Classifier: Topic :: Utilities
Classifier: License :: OSI Approved :: MIT License
Classifier: Programming Language :: Python :: 2.7
